lark_cython/__init__.py
lark_cython/lark_cython.cp39-win_amd64.pyd
lark_cython-0.0.17.dist-info/licenses/LICENSE
lark_cython-0.0.17.dist-info/METADATA
lark_cython-0.0.17.dist-info/WHEEL
lark_cython-0.0.17.dist-info/top_level.txt
lark_cython-0.0.17.dist-info/RECORD
