Metadata-Version: 2.4
Name: lark-cython
Version: 0.0.17
Summary: A Lark plugin that optimizes LALR parsing using Cython
Home-page: https://github.com/lark-parser/lark_cython
Author: Erez Shinan
Author-email: lark@erezsh.com
License: MIT
Keywords: Lark LALR parser optimized Cython
Classifier: Development Status :: 4 - Beta
Classifier: Intended Audience :: Developers
Classifier: Topic :: Software Development :: Libraries :: Python Modules
Classifier: Topic :: Utilities
Classifier: Operating System :: Microsoft :: Windows
Classifier: Operating System :: MacOS
Classifier: Operating System :: POSIX :: Linux
Classifier: License :: OSI Approved :: MIT License
Classifier: Programming Language :: Python :: 3.6
Classifier: Programming Language :: Python :: 3.7
Classifier: Programming Language :: Python :: 3.8
Classifier: Programming Language :: Python :: 3.9
Classifier: Programming Language :: Python :: 3.10
Requires: Cython
Requires-Python: >=3.6
License-File: LICENSE
Requires-Dist: lark>=1.1.7
Dynamic: author
Dynamic: author-email
Dynamic: classifier
Dynamic: description
Dynamic: description-content-type
Dynamic: home-page
Dynamic: keywords
Dynamic: license
Dynamic: license-file
Dynamic: requires
Dynamic: requires-dist
Dynamic: requires-python
Dynamic: summary
